LICENSE
MANIFEST.in
README.md
setup.py
django_mapped_fields.egg-info/PKG-INFO
django_mapped_fields.egg-info/SOURCES.txt
django_mapped_fields.egg-info/dependency_links.txt
django_mapped_fields.egg-info/not-zip-safe
django_mapped_fields.egg-info/top_level.txt
mapped_fields/__init__.py
mapped_fields/fields.py
mapped_fields/widgets.py