Metadata-Version: 1.0
Name: django-mapped-fields
Version: 0.0.2
Summary: Form fields to make it easier to map CSV or JSON files to your own models
Home-page: https://github.com/mypebble/mapped-fields
Author: SF Software limited t/a Pebble
Author-email: sysadmin@talktopebble.co.uk
License: UNKNOWN
Platform: UNKNOWN
